menetools/__init__.py
menetools/__main__.py
menetools/meneacti.py
menetools/menecheck.py
menetools/menecof.py
menetools/menedead.py
menetools/menepath.py
menetools/menescope.py
menetools/menescope_inc.py
menetools/meneseed.py
menetools/query.py
menetools/sbml.py
menetools/utils.py
menetools/encodings/get_activated.lp
menetools/encodings/get_cofs.lp
menetools/encodings/get_cofs_weighted.lp
menetools/encodings/get_deadends.lp
menetools/encodings/get_incremental_scope.lp
menetools/encodings/get_min_paths.lp
menetools/encodings/get_paths.lp
menetools/encodings/get_scope.lp
menetools/encodings/get_seeds.lp
menetools/encodings/get_unproducible_targets.lp
MeneTools-3.4.0.dist-info/LICENSE.txt
MeneTools-3.4.0.dist-info/METADATA
MeneTools-3.4.0.dist-info/WHEEL
MeneTools-3.4.0.dist-info/entry_points.txt
MeneTools-3.4.0.dist-info/top_level.txt
MeneTools-3.4.0.dist-info/RECORD
