Metadata-Version: 2.1
Name: MeneTools
Version: 3.4.0
Summary: Metabolic Network Topology Analysis Tools
Author-email: Clemence Frioux <clemence.frioux@inria.fr>
License: LGPL-3.0-or-later
Project-URL: Homepage, https://github.com/cfrioux/MeneTools
Project-URL: Changelog, https://github.com/cfrioux/MeneTools/blob/main/CHANGELOG.md
Classifier: Programming Language :: Python :: 3.6
Classifier: Programming Language :: Python :: 3.7
Classifier: Programming Language :: Python :: 3.8
Classifier: Operating System :: MacOS :: MacOS X
Classifier: Operating System :: Unix
License-File: LICENSE.txt
Requires-Dist: clyngor-with-clingo
Requires-Dist: clyngor
